poword/__init__.py
poword/api/__init__.py
poword/api/word.py
poword/core/WordType.py
poword/core/__init__.py
poword/lib/__init__.py
tests/__init__.py
tests/test_word.py
poword-0.0.17.dist-info/LICENSE
poword-0.0.17.dist-info/METADATA
poword-0.0.17.dist-info/WHEEL
poword-0.0.17.dist-info/top_level.txt
poword-0.0.17.dist-info/RECORD
