Metadata-Version: 2.1
Name: poword
Version: 0.0.17
Summary: pip install poword
Home-page: https://www.python-office.com/
Author: CoderWanFeng
Author-email: 1957875073@qq.com
License: MIT
Project-URL: Bug Tracker, https://github.com/CoderWanFeng/poword/issues
Project-URL: Documentation, https://github.com/CoderWanFeng/poword/blob/master/README.md
Project-URL: Source Code, https://github.com/CoderWanFeng/poword
Platform: any
Requires-Python: >=3.7
License-File: LICENSE
Requires-Dist: pywin32
Requires-Dist: poprogress
Requires-Dist: pofile
